jetblack_datemath/__init__.py
jetblack_datemath/arithmetic.py
jetblack_datemath/calendars.py
jetblack_datemath/daterules.py
jetblack_datemath/months.py
jetblack_datemath/py.typed
jetblack_datemath/weekdays.py
jetblack_datemath-1.0.1.dist-info/LICENSE
jetblack_datemath-1.0.1.dist-info/WHEEL
jetblack_datemath-1.0.1.dist-info/METADATA
jetblack_datemath-1.0.1.dist-info/RECORD
